invirtualenv/__init__.py
invirtualenv/cli.py
invirtualenv/config.py
invirtualenv/contextmanager.py
invirtualenv/deploy.py
invirtualenv/exceptions.py
invirtualenv/package.py
invirtualenv/plugin.py
invirtualenv/plugin_base.py
invirtualenv/utility.py
invirtualenv/virtualenv.py
invirtualenv-24.9.959143.data/scripts/create_package
invirtualenv-24.9.959143.data/scripts/deploy_virtualenv
invirtualenv-24.9.959143.data/scripts/package_virtualenv_name
invirtualenv_plugins/__init__.py
invirtualenv_plugins/docker.py
invirtualenv_plugins/parsedconfig.py
invirtualenv_plugins/rpm.py
invirtualenv_plugins/docker_scripts/__init__.py
invirtualenv_plugins/docker_scripts/docker_build.sh
invirtualenv_plugins/docker_scripts/docker_build_py
invirtualenv_plugins/docker_scripts/post_build.py
invirtualenv_plugins/rpm_scripts/__init__.py
invirtualenv_plugins/rpm_scripts/post_install.py
invirtualenv_plugins/rpm_scripts/pre_uninstall.py
invirtualenv-24.9.959143.dist-info/LICENSE.txt
invirtualenv-24.9.959143.dist-info/METADATA
invirtualenv-24.9.959143.dist-info/WHEEL
invirtualenv-24.9.959143.dist-info/entry_points.txt
invirtualenv-24.9.959143.dist-info/top_level.txt
invirtualenv-24.9.959143.dist-info/zip-safe
invirtualenv-24.9.959143.dist-info/RECORD
