Metadata-Version: 2.1
Name: invirtualenv
Version: 24.9.959143
Summary: Tool to abstract host deployment of Python packages
Home-page: https://github.com/yahoo/invirtualenv
Author: Dwight Hubbard
Author-email: 254983+dwighthubbard@users.noreply.github.com
License: BSD License
Project-URL: Source Code, https://github.com/yahoo/invirtualenv
Project-URL: Documentation, https://invirtualenv.readthedocs.io/en/latest/?badge=latest
Keywords: packaging deployment
Classifier: License :: OSI Approved :: BSD License
Classifier: Programming Language :: Python :: 3
Classifier: Programming Language :: Python :: 3.6
Classifier: Programming Language :: Python :: 3.7
Classifier: Programming Language :: Python :: 3.8
Classifier: Programming Language :: Python :: 3.9
Requires-Python: >=2.7.5
License-File: LICENSE.txt
Requires-Dist: defusedxml
Requires-Dist: distro
Requires-Dist: jinja2
Requires-Dist: requests>=2.22.0
Requires-Dist: six>=1.5
Requires-Dist: virtualenv<20.22.0
Requires-Dist: wheel
Requires-Dist: urllib3
Requires-Dist: configparser; python_version < "3.4"
Provides-Extra: doc_build
Requires-Dist: sphinx; extra == "doc-build"
Requires-Dist: sphinx-bootstrap-theme; extra == "doc-build"
Requires-Dist: guzzle-sphinx-theme; extra == "doc-build"
Requires-Dist: sphinx-rtd-theme; extra == "doc-build"
Requires-Dist: recommonmark; extra == "doc-build"
Provides-Extra: test
Requires-Dist: pytest; extra == "test"
Requires-Dist: pytest-cov; extra == "test"
Requires-Dist: vcrpy-unittest; extra == "test"
